mprofile-0.0.15.dist-info/METADATA
mprofile-0.0.15.dist-info/LICENSE
mprofile-0.0.15.dist-info/top_level.txt
mprofile-0.0.15.dist-info/WHEEL
mprofile-0.0.15.dist-info/RECORD
mprofile/__init__.py
mprofile/_profiler.cpython-310-x86_64-linux-gnu.so
