Metadata-Version: 2.1
Name: mprofile
Version: 0.0.15
Summary: A low-overhead memory profiler.
Home-page: http://github.com/timpalpant/mprofile
Author: Timothy Palpant
Author-email: tim@palpant.us
License: MIT
Project-URL: Source, https://github.com/timpalpant/mprofile
Project-URL: Tracker, https://github.com/timpalpant/mprofile/issues
Keywords: profiling performance
Platform: Mac OS X
Platform: POSIX
Classifier: Development Status :: 2 - Pre-Alpha
Classifier: Intended Audience :: Developers
Classifier: License :: OSI Approved :: GNU Lesser General Public License v3 (LGPLv3)
Classifier: Operating System :: POSIX
Classifier: Programming Language :: Python :: 3.6
Classifier: Programming Language :: Python :: 3.7
Classifier: Programming Language :: Python :: 3.8
Classifier: Programming Language :: Python :: 3.9
Classifier: Programming Language :: Python :: 3.10
Classifier: Programming Language :: Python :: 3.11
Classifier: Programming Language :: Python :: Implementation :: CPython
Classifier: Topic :: Software Development :: Testing
Classifier: Topic :: Software Development :: Libraries :: Python Modules
License-File: LICENSE
